ctpnet/__init__.py
ctpnet/network.py
ctpnet/predict.py
cTPnet-0.2.6.dist-info/LICENSE
cTPnet-0.2.6.dist-info/METADATA
cTPnet-0.2.6.dist-info/WHEEL
cTPnet-0.2.6.dist-info/top_level.txt
cTPnet-0.2.6.dist-info/RECORD
